r6statsapi/__init__.py
r6statsapi/client.py
r6statsapi/enums.py
r6statsapi/errors.py
r6statsapi/player.py
r6statsapi-0.1.9.dist-info/LICENSE
r6statsapi-0.1.9.dist-info/METADATA
r6statsapi-0.1.9.dist-info/WHEEL
r6statsapi-0.1.9.dist-info/top_level.txt
r6statsapi-0.1.9.dist-info/RECORD
